kerch/__init__.py
kerch/_cache.py
kerch/_dataholder.py
kerch/_logger.py
kerch/_module.py
kerch/_sample.py
kerch/_stochastic.py
kerch-0.3.1.5.dist-info/LICENSE
kerch-0.3.1.5.dist-info/METADATA
kerch-0.3.1.5.dist-info/WHEEL
kerch-0.3.1.5.dist-info/top_level.txt
kerch-0.3.1.5.dist-info/RECORD
