Metadata-Version: 2.1
Name: kerch
Version: 0.3.1.5
Summary: Kernel Methods in PyTorch
Author-email: Henri DE PLAEN <henri.deplaen@gmail.com>
License: GNU LESSER GENERAL PUBLIC LICENSE
Project-URL: Homepage, https://github.com/hdeplaen/kerch
Project-URL: GitHub, https://github.com/hdeplaen/kerch
Project-URL: Documentation, https://kerch.readthedocs.io/en/latest/
Project-URL: Issues, https://github.com/hdeplaen/kerch/issues
Project-URL: Bug-Tracker, https://github.com/hdeplaen/kerch/issues
Project-URL: E-DUALITY, https://www.esat.kuleuven.be/stadius/E/
Project-URL: ESAT-STADIUS, https://www.esat.kuleuven.be/stadius/
Keywords: pytorch,machine learning
Classifier: Development Status :: 4 - Beta
Classifier: Environment :: GPU :: NVIDIA CUDA
Classifier: Intended Audience :: Developers
Classifier: Intended Audience :: Education
Classifier: Intended Audience :: Science/Research
Classifier: Natural Language :: English
Classifier: Operating System :: MacOS
Classifier: Operating System :: Microsoft :: Windows
Classifier: Operating System :: OS Independent
Classifier: Operating System :: POSIX
Classifier: Operating System :: POSIX :: Linux
Classifier: Programming Language :: C++
Classifier: Programming Language :: Python :: 3
Classifier: Programming Language :: Python :: 3.10
Classifier: Programming Language :: Python :: 3.11
Classifier: Programming Language :: Python :: 3.12
Classifier: Programming Language :: Python :: 3.8
Classifier: Programming Language :: Python :: 3.9
Classifier: Topic :: Software Development :: Libraries :: Python Modules
Classifier: Topic :: Scientific/Engineering :: Artificial Intelligence
Classifier: Topic :: Scientific/Engineering :: Information Analysis
Classifier: Topic :: Scientific/Engineering :: Mathematics
Classifier: Topic :: Software Development :: Libraries :: Python Modules
Classifier: Topic :: Utilities
Requires-Python: >=3.8
License-File: LICENSE
Requires-Dist: torch
Requires-Dist: matplotlib
Requires-Dist: numpy
Requires-Dist: pyyaml
Requires-Dist: tqdm
Requires-Dist: nested-dict
Requires-Dist: optuna
Requires-Dist: lazy-loader
Requires-Dist: wandb
